{"cameraMode":{"drawMode":0,"name":"Shaded","section":"Shading Mode"},"sceneLighting":true,"audioPlay":false,"sceneViewState":{"showFog":true,"showMaterialUpdate":false,"showSkybox":true,"showFlares":true,"showImageEffects":true,"showParticleSystems":true},"in2DMode":false,"pivot":{"x":-314.4636535644531,"y":-131.9933319091797,"z":1318.0201416015625},"rotation":{"x":0.22295552492141725,"y":-0.4084763824939728,"z":0.10360436141490936,"w":0.8790358901023865},"size":609.4581298828125,"orthographic":false}